pyramid_restful/__init__.py
pyramid_restful/_version.py
pyramid_restful/api.py
pyramid_restful/documentation.py
pyramid_restful/endpoint.py
pyramid_restful/renderer.py
pyramid_restful/services.py
pyramid_restful/utils.py
pyramid_restful/templates/documentation.html.jinja
pyramid_restful/templates/introduction.md.jinja
pyramid_restful-2016.0.46.dist-info/DESCRIPTION.rst
pyramid_restful-2016.0.46.dist-info/METADATA
pyramid_restful-2016.0.46.dist-info/metadata.json
pyramid_restful-2016.0.46.dist-info/RECORD
pyramid_restful-2016.0.46.dist-info/top_level.txt
pyramid_restful-2016.0.46.dist-info/WHEEL
tests/__init__.py
tests/conftest.py
tests/oauth.py
tests/test_actions.py
tests/test_authenticated.py
tests/test_basics.py
tests/test_classes.py
tests/test_endpoints.py
tests/test_modules.py
tests/test_utils.py
