Metadata-Version: 2.0
Name: pyramid-restful
Version: 2016.0.46
Summary: Library for generating RESTful services with Pyramid.
Home-page: https://github.com/bitesofcode/pyramid_restful
Author: Eric Hulser
Author-email: eric.hulser@gmail.com
License: MIT
Platform: UNKNOWN
Requires-Dist: projex
Requires-Dist: pyramid
Requires-Dist: markdown
Requires-Dist: jinja2
